hurst_exponent/__init__.py
hurst_exponent/acf.py
hurst_exponent/hurst_exponent.py
hurst_exponent-1.0.1.dist-info/LICENSE
hurst_exponent-1.0.1.dist-info/METADATA
hurst_exponent-1.0.1.dist-info/WHEEL
hurst_exponent-1.0.1.dist-info/RECORD
