Metadata-Version: 2.1
Name: hurst-exponent
Version: 1.0.1
Summary: Hurst exponent estimator
Home-page: https://github.com/anabugaenko/hurst_exponent
License: MIT
Keywords: hurst,autocorrelation,time-series,fractals
Author: Anastasia Bugeenko
Author-email: anabugaenko@gmail.com
Requires-Python: >=3.9,<4.0
Classifier: Intended Audience :: Science/Research
Classifier: License :: OSI Approved :: MIT License
Classifier: Operating System :: OS Independent
Classifier: Programming Language :: Python :: 3
Classifier: Programming Language :: Python :: 3.9
Classifier: Programming Language :: Python :: 3.10
Classifier: Programming Language :: Python :: 3.11
Classifier: Topic :: Scientific/Engineering :: Mathematics
Requires-Dist: matplotlib
Requires-Dist: numpy
Requires-Dist: pandas
Requires-Dist: scipy
Requires-Dist: statsmodels
Requires-Dist: stochastic
Requires-Dist: typing
Project-URL: Repository, https://github.com/anabugaenko/hurst_exponent
